awsgi2/__init__.py
awsgi2/base.py
awsgi2/impl.py
awsgi2/py.typed
awsgi2/utilities.py
awsgi2/wrapper.py
awsgi2/wsgienv.py
awsgi2-1.0.2.dist-info/LICENSE
awsgi2-1.0.2.dist-info/METADATA
awsgi2-1.0.2.dist-info/WHEEL
awsgi2-1.0.2.dist-info/RECORD
