Metadata-Version: 2.1
Name: awsgi2
Version: 1.0.2
Summary: A WSGI gateway for the AWS API Gateway/Lambda proxy integration
Home-page: https://gitlab.com/advian-oss/python-awsgi2/
License: MIT
Author: Eero af Heurlin
Author-email: eero.afheurlin@advian.fi
Requires-Python: >=3.8,<4.0
Classifier: License :: OSI Approved :: MIT License
Classifier: Programming Language :: Python :: 3
Classifier: Programming Language :: Python :: 3.8
Classifier: Programming Language :: Python :: 3.9
Classifier: Programming Language :: Python :: 3.10
Classifier: Programming Language :: Python :: 3.11
Classifier: Programming Language :: Python :: 3.12
Requires-Dist: libadvian (>=1.3,<2.0)
Project-URL: Repository, https://gitlab.com/advian-oss/python-awsgi2/
